celerycontrib.sqlalchemyscheduler-0.1.0-py3.4-nspkg.pth
celerycontrib.sqlalchemyscheduler-0.1.0.dist-info/top_level.txt
celerycontrib.sqlalchemyscheduler-0.1.0.dist-info/RECORD
celerycontrib.sqlalchemyscheduler-0.1.0.dist-info/METADATA
celerycontrib.sqlalchemyscheduler-0.1.0.dist-info/DESCRIPTION.rst
celerycontrib.sqlalchemyscheduler-0.1.0.dist-info/namespace_packages.txt
celerycontrib.sqlalchemyscheduler-0.1.0.dist-info/metadata.json
celerycontrib.sqlalchemyscheduler-0.1.0.dist-info/WHEEL
celerycontrib/sqlalchemyscheduler/model.py
celerycontrib/sqlalchemyscheduler/scheduler.py
celerycontrib/sqlalchemyscheduler/__init__.py
