Metadata-Version: 2.0
Name: celerycontrib.sqlalchemyscheduler
Version: 0.1.0
Summary: SQLAlchemy-backed scheduler for Celery
Home-page: UNKNOWN
Author: Arthur Blair
Author-email: adblair@gmail.com
License: UNKNOWN
Keywords: celerycontrib.sqlalchemyscheduler
Platform: UNKNOWN
Classifier: Natural Language :: English
Classifier: Programming Language :: Python :: 3
Requires-Dist: celery
Requires-Dist: pretty-cron
Requires-Dist: sqlalchemy
